xkynet/__init__.py
xkynet/graphrag/__init__.py
xkynet/graphrag/callbacks.py
xkynet/graphrag/indexer.py
xkynet/graphrag/intializer.py
xkynet/graphrag/searcher.py
xkynet/graphrag/utils.py
xkynet/openai/__init__.py
xkynet/openai/assistant.py
xkynet/openai/callbacks.py
xkynet/openai/utils.py
xkynet-0.0.2.dist-info/METADATA
xkynet-0.0.2.dist-info/WHEEL
xkynet-0.0.2.dist-info/top_level.txt
xkynet-0.0.2.dist-info/RECORD
